ec2_ssm_connect/__init__.py
ec2_ssm_connect/main.py
ec2_ssm_connect-0.1.5.dist-info/LICENSE
ec2_ssm_connect-0.1.5.dist-info/METADATA
ec2_ssm_connect-0.1.5.dist-info/WHEEL
ec2_ssm_connect-0.1.5.dist-info/entry_points.txt
ec2_ssm_connect-0.1.5.dist-info/top_level.txt
ec2_ssm_connect-0.1.5.dist-info/RECORD
