Metadata-Version: 2.1
Name: ec2-ssm-connect
Version: 0.1.5
Summary: An interactive command-line tool to list Amazon EC2 instances and establish secure connections using AWS Systems Manager (SSM) Session Manager.
Home-page: https://www.github.com/ingomarlos/ec2-ssm-connect
Author: Ingo Marlos Batista de Sousa
Author-email: your.email@example.com
Keywords: aws,ec2,ssm,systems manager,session manager
Classifier: Development Status :: 3 - Alpha
Classifier: Intended Audience :: Developers
Classifier: Programming Language :: Python :: 3
Classifier: Programming Language :: Python :: 3.9
Classifier: Operating System :: Unix
Classifier: Operating System :: MacOS :: MacOS X
Classifier: Operating System :: Microsoft :: Windows
Requires-Python: >=3.9
License-File: LICENSE
Requires-Dist: boto3
